pset1/__init__.py
pset1/__main__.py
pset1/canvas.py
pset1/hash_str.py
pset1/io.py
pset1nik-0.1.4.dist-info/LICENSE
pset1nik-0.1.4.dist-info/METADATA
pset1nik-0.1.4.dist-info/WHEEL
pset1nik-0.1.4.dist-info/top_level.txt
pset1nik-0.1.4.dist-info/RECORD
