Metadata-Version: 2.1
Name: pset1nik
Version: 0.1.4
Summary: pset1 test
Home-page: https://github.com/nikhar1210
Author: Nikhar
Author-email: nikhar1210@gmail.com
License: UNKNOWN
Platform: UNKNOWN
Classifier: Programming Language :: Python :: 3.7
Classifier: Programming Language :: Python :: 3.8
Classifier: License :: OSI Approved :: GNU General Public License v2 or later (GPLv2+)
Classifier: Operating System :: OS Independent
Requires-Dist: xlrd (==1.2.0)
Requires-Dist: canvasapi (>=2.1.0)
Requires-Dist: environs (>=9.3.1)
Requires-Dist: awscli (>=1.19.12)
